gdemux
