Metadata-Version: 1.1
Name: gdemux
Version: 0.0.2
Summary: Almost pointless demultiplexer
Home-page: http://github.com/brwnj/gdemux
Author: Joe Brown
Author-email: joe.brown@pnnl.gov
License: Unlicense
Download-URL: https://github.com/brwnj/gdemux/archive/0.0.1.tar.gz
Platform: UNKNOWN
